{
    "featuredVideo" : "https://web.microsoftstream.com/embed/video/cd0777c4-c301-4a64-839c-244f9d981311?autoplay=false&showinfo=false",

    "techTalks": {
        "channelUrl": "https://web.microsoftstream.com/embed/channel/33f159ae-3ef0-4b20-89b4-3a36ad9580ae?sort=date",
        "featuredVideo": "https://web.microsoftstream.com/embed/video/cd0777c4-c301-4a64-839c-244f9d981311?autoplay=false&showinfo=false",
        "live": {
          "active":true,  
          "title": "TechTalks August 2022",
          "summary": "Announcing: Harbor Container Platform @ NS",
          "link": "https://go.nstech.events/tt",
          "start": "2022-08-24T08:00:00.000Z",
          "end": "2022-08-24T09:00:00.000Z"
        }
    },
    "techBits": {
        "channelUrl": "https://web.microsoftstream.com/embed/channel/2e02816b-554e-4781-8e11-82262222d920?sort=date",
        "featuredVideo": "https://web.microsoftstream.com/embed/video/cd0777c4-c301-4a64-839c-244f9d981311?autoplay=false&showinfo=false"
    }
}
